Metadata-Version: 1.0
Name: geeksdownloader
Version: 1.0
Summary: Download all GeeksforGeeks articles/posts of a particular topic/company within a minute
Home-page: https://github.com/madhuradlakha/GeeksforGeeks_Downloader
Author: Madhur Adlakha
Author-email: madhuradlakha@yahoo.co.in
License: MIT
Platform: UNKNOWN
